fujitsu_sdt_mcp/__init__.py
fujitsu_sdt_mcp/__main__.py
fujitsu_sdt_mcp/server.py
mseep_fujitsu_sdt_mcp-0.1.2.dist-info/licenses/LICENSE
mseep_fujitsu_sdt_mcp-0.1.2.dist-info/METADATA
mseep_fujitsu_sdt_mcp-0.1.2.dist-info/WHEEL
mseep_fujitsu_sdt_mcp-0.1.2.dist-info/entry_points.txt
mseep_fujitsu_sdt_mcp-0.1.2.dist-info/top_level.txt
mseep_fujitsu_sdt_mcp-0.1.2.dist-info/RECORD
